pysonos/__init__.py
pysonos/alarms.py
pysonos/cache.py
pysonos/config.py
pysonos/core.py
pysonos/data_structure_quirks.py
pysonos/data_structures.py
pysonos/data_structures_entry.py
pysonos/discovery.py
pysonos/events.py
pysonos/events_asyncio.py
pysonos/events_base.py
pysonos/events_twisted.py
pysonos/exceptions.py
pysonos/groups.py
pysonos/ms_data_structures.py
pysonos/music_library.py
pysonos/services.py
pysonos/snapshot.py
pysonos/soap.py
pysonos/utils.py
pysonos/xml.py
pysonos/music_services/__init__.py
pysonos/music_services/accounts.py
pysonos/music_services/data_structures.py
pysonos/music_services/music_service.py
pysonos/plugins/__init__.py
pysonos/plugins/example.py
pysonos/plugins/sharelink.py
pysonos/plugins/spotify.py
pysonos/plugins/wimp.py
pysonos-0.0.54.dist-info/AUTHORS.rst
pysonos-0.0.54.dist-info/LICENSE.rst
pysonos-0.0.54.dist-info/METADATA
pysonos-0.0.54.dist-info/WHEEL
pysonos-0.0.54.dist-info/top_level.txt
pysonos-0.0.54.dist-info/RECORD
