Metadata-Version: 2.1
Name: pysonos
Version: 0.0.54
Summary: A SoCo fork with fixes for Home Assistant.
Home-page: https://github.com/amelchio/pysonos
Author: Anders Melchiorsen
Author-email: amelchio@nogoto.net
License: MIT License
Platform: UNKNOWN
Classifier: Development Status :: 4 - Beta
Classifier: Intended Audience :: Developers
Classifier: License :: OSI Approved :: MIT License
Classifier: Operating System :: OS Independent
Classifier: Programming Language :: Python :: 3.7
Classifier: Programming Language :: Python :: 3.8
Classifier: Programming Language :: Python :: 3.9
Classifier: Programming Language :: Python :: 3 :: Only
Classifier: Programming Language :: Python :: Implementation :: CPython
Classifier: Programming Language :: Python :: Implementation :: PyPy
Classifier: Topic :: Home Automation
Classifier: Topic :: Multimedia :: Sound/Audio
Classifier: Topic :: Multimedia :: Sound/Audio :: Players
Classifier: Topic :: Software Development :: Libraries :: Python Modules
Requires-Python: >=3.7
Requires-Dist: requests
Requires-Dist: xmltodict
Requires-Dist: ifaddr
Provides-Extra: events_asyncio
Requires-Dist: aiohttp ; extra == 'events_asyncio'
